checkpointed/__init__.py
checkpointed-1.0.0.dist-info/LICENSE
checkpointed-1.0.0.dist-info/METADATA
checkpointed-1.0.0.dist-info/WHEEL
checkpointed-1.0.0.dist-info/top_level.txt
checkpointed-1.0.0.dist-info/RECORD
